isaadvmutility/__init__.py
isaadvmutility/advmutility.py
isaadvmutility/configurator.py
isaadvmutility/datastore.py
isaadvmutility/logger.py
isaadvmutility/msgraphapi.py
isaadvmutility/pgdbconnection.py
isaadvmutility/qualys_dao.py
isaadvmutility/rabbitmq.py
isaadvmutility/splunk_forwarder.py
isaadvmutility-1.3.5.dist-info/METADATA
isaadvmutility-1.3.5.dist-info/WHEEL
isaadvmutility-1.3.5.dist-info/RECORD
